{
  "documentId": "c1bac23b694aeba7",
  "pageNumber": 6,
  "title": "Page 6: 证券研究报告",
  "preview": "证券研究报告 国信证券经济研究所 深圳 深圳市福田区福华一路 125 号国信金融大厦 36 层 邮编：518046 总机：0755-82130833 上海 上海浦东民生路 1199 弄证大五道口广场 1 号楼 12 层 邮编：200135 北京 北京西城区金融大街兴盛街 6 号国信证券 9 层 邮编：100032",
  "text": "证券研究报告\r\n国信证券经济研究所\r\n深圳\r\n深圳市福田区福华一路 125 号国信金融大厦 36 层\r\n邮编：518046 总机：0755-82130833\r\n上海\r\n上海浦东民生路 1199 弄证大五道口广场 1 号楼 12 层\r\n邮编：200135\r\n北京\r\n北京西城区金融大街兴盛街 6 号国信证券 9 层\r\n邮编：100032",
  "chars": 167,
  "artifactPath": "/Users/huangjinfeng/workspace/echofiles/echo-pdf/.echo-pdf-workspace/documents/c1bac23b694aeba7/pages/0006.json"
}
